{
  "id": "finance-personal",
  "icon": "💰",
  "name": "个人理财与财务规划",
  "desc": "中国语境的实操理财：五险一金、房贷、保险、基金定投、养老与 FIRE。",
  "tracks": [
    { "tag": "理财 · 地基", "name": "现金流与制度", "clusters": [
      { "name": "现金流管理", "topics": [
        "记账的最小可行做法", "预算法（50/30/20 及其变体）", "应急基金：几个月才够", "储蓄率是第一杠杆",
        "净资产表：个人资产负债观", "现金类工具对比（活期/货基/T+0理财）", "国债逆回购的节假日套利", "存款利率与挂牌价",
        "消费降级与生活方式通胀", "订阅制陷阱与年度账单体检"
      ] },
      { "name": "五险一金与个税", "topics": [
        "五险一金每一项是什么", "社保缴费基数与上下限", "养老金：统筹账户与个人账户", "养老金领取公式与缴费年限",
        "医保：统筹/个账/门诊共济", "公积金：提取与贷款额度", "个税累进税率与速算", "专项附加扣除清单",
        "年终奖单独计税的选择", "个人养老金账户（税收递延）", "灵活就业的社保策略", "异地转移与断缴的影响"
      ] },
      { "name": "信用与负债", "topics": [
        "征信报告怎么读", "信用卡的正确用法（免息期/分期真实利率）", "IRR：看穿一切分期", "消费贷与经营贷的边界",
        "好负债与坏负债", "债务雪球 vs 债务雪崩", "网贷的代价", "担保与连带责任的坑"
      ] }
    ] },
    { "tag": "理财 · 大件", "name": "房产与保险", "clusters": [
      { "name": "房产", "topics": [
        "LPR 与房贷利率定价", "等额本息 vs 等额本金", "提前还款的数学（何时划算）", "租售比与持有成本",
        "买房全流程成本清单（税费/中介/评估）", "公积金贷款组合贷", "二手房交易的风险点", "限购限售与政策周期",
        "房产在家庭资产中的占比", "租房 vs 买房的决策框架"
      ] },
      { "name": "保险配置", "topics": [
        "保险的本质：转移无法承受的风险", "四大件：医疗/重疾/定寿/意外", "百万医疗险的免赔额与续保", "重疾险：保额怎么定",
        "定期寿险：家庭支柱的底线", "意外险的杠杆", "年金与增额终身寿的收益真相", "健康告知与拒赔争议",
        "给孩子和父母买什么", "保费占收入的合理比例", "理赔流程与材料", "「返还型」的机会成本"
      ] }
    ] },
    { "tag": "理财 · 投资实操", "name": "基金与投资实操", "clusters": [
      { "name": "基金实操", "topics": [
        "场内 ETF vs 场外基金", "A/C 份额与持有期限", "申赎费/管理费/托管费全解", "指数基金与增强指数",
        "主动基金的选择维度（双十/换手/回撤）", "定投的本质与适用场景", "止盈策略（目标/估值/回撤）", "QDII 与跨境投资（额度/溢价）",
        "联接基金与跟踪误差", "基金经理变更的应对", "FOF 与投顾组合", "分红方式：现金 vs 再投资"
      ] },
      { "name": "贵金属与另类", "topics": [
        "积存金/纸黄金/金 ETF/实物金对比", "金价的三大驱动（实际利率/美元/避险）", "银行积存金的点差与费用", "黄金在配置中的角色与比例",
        "白银的工业属性", "收藏品与「另类投资」的流动性陷阱", "外币存款与汇率风险"
      ] },
      { "name": "防骗与安全", "topics": [
        "庞氏骗局的识别特征", "「保本高息」不可能三角", "杀猪盘与情感诈骗话术", "非法集资与私募暴雷案例",
        "电信诈骗的常见剧本", "个人信息保护清单", "家庭账户安全（密码/二步验证）", "帮父母建立防骗免疫"
      ] }
    ] },
    { "tag": "理财 · 远期", "name": "养老与人生财务", "clusters": [
      { "name": "复利与目标", "topics": [
        "复利的真实速度（72 法则）", "通胀对购买力的侵蚀", "FIRE 与 4% 法则及其中国适配", "财务自由的分级（瘦/肥/咖啡师）",
        "人力资本：最大的资产是自己", "收入多元化（主业/副业/资产）", "目标倒推法：从数字到月供", "序列风险：退休前后的回撤杀伤"
      ] },
      { "name": "家庭与传承", "topics": [
        "家庭财务的「四个账户」框架", "夫妻财务的共管模式", "子女教育金的规划", "赡养与三明治一代的现金流",
        "遗嘱与法定继承顺序", "大额保单的传承功能", "婚前财产与公证", "突发风险预案（重病/失业）清单"
      ] }
    ] }
  ]
}
